{
  "main": {
    "id": "130743ffdf151392",
    "type": "split",
    "children": [
      {
        "id": "9203b0d6c32dd176",
        "type": "tabs",
        "children": [
          {
            "id": "7de34acf6d99d1fd",
            "type": "leaf",
            "state": {
              "type": "canvas",
              "state": {
                "file": "Bash.canvas",
                "viewState": {
                  "x": 1207,
                  "y": 2680.5,
                  "zoom": -3.228391161957891
                }
              },
              "icon": "lucide-layout-dashboard",
              "title": "Bash"
            }
          }
        ]
      }
    ],
    "direction": "vertical"
  },
  "left": {
    "id": "b8235a884e24e9b9",
    "type": "split",
    "children": [
      {
        "id": "f56f6eb75afbed42",
        "type": "tabs",
        "children": [
          {
            "id": "ebc4ea967b699565",
            "type": "leaf",
            "state": {
              "type": "file-explorer",
              "state": {
                "sortOrder": "alphabetical",
                "autoReveal": false
              },
              "icon": "lucide-folder-closed",
              "title": "Files"
            }
          },
          {
            "id": "23a32d7415626557",
            "type": "leaf",
            "state": {
              "type": "search",
              "state": {
                "query": "",
                "matchingCase": true,
                "explainSearch": false,
                "collapseAll": false,
                "extraContext": false,
                "sortOrder": "alphabetical"
              },
              "icon": "lucide-search",
              "title": "Search"
            }
          },
          {
            "id": "0f739b3809ae9347",
            "type": "leaf",
            "state": {
              "type": "bookmarks",
              "state": {},
              "icon": "lucide-bookmark",
              "title": "Bookmarks"
            }
          }
        ]
      }
    ],
    "direction": "horizontal",
    "width": 520.5
  },
  "right": {
    "id": "44ef85c9389af807",
    "type": "split",
    "children": [
      {
        "id": "03bc6924d609fbca",
        "type": "tabs",
        "children": [
          {
            "id": "2e65c3839b7a00ee",
            "type": "leaf",
            "state": {
              "type": "backlink",
              "state": {
                "file": "Untitled.md",
                "collapseAll": false,
                "extraContext": false,
                "sortOrder": "alphabetical",
                "showSearch": false,
                "searchQuery": "",
                "backlinkCollapsed": false,
                "unlinkedCollapsed": true
              },
              "icon": "links-coming-in",
              "title": "Backlinks for Untitled"
            }
          },
          {
            "id": "4f668e4057a7ce91",
            "type": "leaf",
            "state": {
              "type": "outgoing-link",
              "state": {
                "file": "Untitled.md",
                "linksCollapsed": false,
                "unlinkedCollapsed": true
              },
              "icon": "links-going-out",
              "title": "Outgoing links from Untitled"
            }
          },
          {
            "id": "eea6350005297997",
            "type": "leaf",
            "state": {
              "type": "tag",
              "state": {
                "sortOrder": "frequency",
                "useHierarchy": true
              },
              "icon": "lucide-tags",
              "title": "Tags"
            }
          },
          {
            "id": "0e825450c87a2abf",
            "type": "leaf",
            "state": {
              "type": "outline",
              "state": {
                "file": "Untitled.md"
              },
              "icon": "lucide-list",
              "title": "Outline of Untitled"
            }
          }
        ]
      }
    ],
    "direction": "horizontal",
    "width": 300,
    "collapsed": true
  },
  "left-ribbon": {
    "hiddenItems": {
      "switcher:Open quick switcher": false,
      "graph:Open graph view": false,
      "canvas:Create new canvas": false,
      "daily-notes:Open today's daily note": false,
      "command-palette:Open command palette": false,
      "templates:Insert template": false
    }
  },
  "active": "7de34acf6d99d1fd",
  "lastOpenFiles": [
    "Advanced python + some web + some db.canvas",
    "Assistant.canvas",
    "Pasted image 20250602140151.png",
    "Some android stuff.canvas",
    "Pomodoro Bot.canvas",
    "Patterns.canvas",
    "Bash.canvas",
    "Compose.md",
    "Pasted image 20250610120613.png",
    "Pasted image 20250610101027.png",
    "Web.canvas",
    "Android basics.md",
    "Docker.canvas",
    "Pasted image 20250609125326.png",
    "Pasted image 20250609122246.png",
    "Pasted image 20250609113606.png",
    "Git.canvas",
    "My app.md",
    "Pasted image 20240825112548.png",
    "Pasted image 20250601192243.png",
    "States in Compose.md",
    "Networks.canvas",
    "Jetpack Compose.md",
    "eb2d6637.png",
    "Coroutines.md",
    "App architecture.md",
    "todo MVVM.md",
    "Pasted image 20250601193340.png",
    "Untitled.md",
    "Welcome.md"
  ]
}